odt_pdf/__init__.py
odt_pdf/odt_to_pdf.py
odt_pdf/pdt_to_text.py
odt_pdf-0.1.0.dist-info/METADATA
odt_pdf-0.1.0.dist-info/WHEEL
odt_pdf-0.1.0.dist-info/RECORD
