Metadata-Version: 2.1
Name: odt-pdf
Version: 0.1.0
Summary: 
Author: levyvix
Author-email: levy.vix@gmail.com
Requires-Python: >=3.11,<4.0
Classifier: Programming Language :: Python :: 3
Classifier: Programming Language :: Python :: 3.11
Classifier: Programming Language :: Python :: 3.12
Requires-Dist: ignr (>=2.2,<3.0)
Requires-Dist: pypdf (>=4.2.0,<5.0.0)
